<?xml version="1.0"?>
<!DOCTYPE hibernate-mapping PUBLIC "-//Hibernate/Hibernate Mapping DTD 3.0//EN"
"http://hibernate.sourceforge.net/hibernate-mapping-3.0.dtd">
<!-- 
    Mapping file autogenerated by MyEclipse - Hibernate Tools
-->
<hibernate-mapping>
    <class name="com.aceway.common.db.entity.AdTaskResult" table="AD_TASK_RESULT" >
        <id name="taskid" type="java.lang.Integer">
            <column name="TASKID" />
            <generator class="hilo" />
        </id>
        <property name="runstarttime" type="java.util.Date">
            <column name="RUNSTARTTIME" length="10" />
        </property>
        <property name="runendtime" type="java.util.Date">
            <column name="RUNENDTIME" length="10" />
        </property>
        <property name="submitsum" type="java.lang.Integer">
            <column name="SUBMITSUM" />
        </property>
        <property name="validsubmitsum" type="java.lang.Integer">
            <column name="VALIDSUBMITSUM" />
        </property>
        <property name="successsum" type="java.lang.Integer">
            <column name="SUCCESSSUM" />
        </property>
        <property name="unknownsum" type="java.lang.Integer">
            <column name="UNKNOWNSUM" />
        </property>
        <property name="failuresum" type="java.lang.Integer">
            <column name="FAILURESUM" />
        </property>
        <property name="canceledsum" type="java.lang.Integer">
            <column name="CANCELEDSUM" />
        </property>
        <property name="resultdesc" type="java.lang.String">
            <column name="RESULTDESC" />
        </property>
    </class>
</hibernate-mapping>
