<?xml version="1.0" encoding="utf-8"?>
<!DOCTYPE hibernate-mapping PUBLIC "-//Hibernate/Hibernate Mapping DTD 3.0//EN"
"http://hibernate.sourceforge.net/hibernate-mapping-3.0.dtd">
<!-- 
    Mapping file autogenerated by MyEclipse Persistence Tools
-->
<hibernate-mapping>
    <class name="com.aceway.common.db.entity.MobileTypeInfo" table="MOBILE_TYPE_INFO" >
        <id name="mobiletypeid" type="java.lang.Integer">
            <column name="MOBILETYPEID" />
            <generator class="hilo" />
        </id>
        <property name="vendername" type="java.lang.String">
            <column name="VENDERNAME" length="50" />
        </property>
        <property name="mobiletypename" type="java.lang.String">
            <column name="MOBILETYPENAME" length="50" />
        </property>
        <property name="pictype" type="java.lang.String">
            <column name="PICTYPE" length="30" />
        </property>
        <property name="audiotype" type="java.lang.String">
            <column name="AUDIOTYPE" length="30" />
        </property>
        <property name="polyphonicnum" type="java.lang.Integer">
            <column name="POLYPHONICNUM" />
        </property>
        <property name="videotype" type="java.lang.String">
            <column name="VIDEOTYPE" length="50" />
        </property>
        <property name="charset" type="java.lang.String">
            <column name="CHARSET" length="30" />
        </property>
        <property name="screencolor" type="java.lang.Integer">
            <column name="SCREENCOLOR" />
        </property>
        <property name="smilspt" type="java.lang.String">
            <column name="SMILSPT" length="1" />
        </property>
        <property name="wapspt" type="java.lang.String">
            <column name="WAPSPT" length="1" />
        </property>
        <property name="mmsspt" type="java.lang.String">
            <column name="MMSSPT" length="1" />
        </property>
        <property name="wappushspt" type="java.lang.String">
            <column name="WAPPUSHSPT" length="1" />
        </property>
        <property name="mmsmaxval" type="java.lang.Integer">
            <column name="MMSMAXVAL" />
        </property>
        <property name="uaname" type="java.lang.String">
            <column name="UANAME" length="100" />
        </property>
        <property name="screensize" type="java.lang.String">
            <column name="SCREENSIZE" length="50" />
        </property>
         <property name="UA_URL" type="java.lang.String">
            <column name="UA_URL" length="50" />
        </property>
        <many-to-one name="uaType"
         class="com.aceway.mms.adaptermanage.model.UAType"
         cascade="none"
         >
         <column name="uatypeid"></column>
        </many-to-one>
        <!--  <set name="uaType" table="ua_type_detail" lazy="false" inverse="false" cascade="none">
        	<key column="UAID"></key>
        	<many-to-many class="com.aceway.common.db.entity.UAType" column="TYPEID" />
        </set>-->
    </class>
</hibernate-mapping>
